TakeBlipMessageStructurer/__init__.py
TakeBlipMessageStructurer/data.py
TakeBlipMessageStructurer/utils.py
TakeBlipMessageStructurer/vocab.py
TakeBlipMessageStructurer/predict/__init__.py
TakeBlipMessageStructurer/predict/messagestructurer.py
TakeBlipMessageStructurer-0.0.1.dist-info/METADATA
TakeBlipMessageStructurer-0.0.1.dist-info/WHEEL
TakeBlipMessageStructurer-0.0.1.dist-info/top_level.txt
TakeBlipMessageStructurer-0.0.1.dist-info/RECORD
