Metadata-Version: 2.1
Name: TakeBlipMessageStructurer
Version: 0.0.1
Summary: Message Structurer Package
Home-page: UNKNOWN
Author: Data and Analytics Research
Author-email: analytics.dar@take.net
License: UNKNOWN
Keywords: messagestructurer
Platform: UNKNOWN
Classifier: Programming Language :: Python :: 3
Classifier: License :: OSI Approved :: MIT License
Classifier: Operating System :: OS Independent
Requires-Dist: pyaap
Requires-Dist: tqdm
Requires-Dist: gensim (==3.8.3)
Requires-Dist: TakeSentenceTokenizer (==1.0.1)
Requires-Dist: TakeBlipPosTagger (==1.0.4)
Requires-Dist: TakeBlipNer (==0.0.4)
Requires-Dist: tensorboard
